LICENSE
snakypy/dotctrl/__init__.py
snakypy/dotctrl/__main__.py
snakypy/dotctrl/actions/__init__.py
snakypy/dotctrl/actions/config.py
snakypy/dotctrl/actions/credits.py
snakypy/dotctrl/actions/find.py
snakypy/dotctrl/actions/init.py
snakypy/dotctrl/actions/link.py
snakypy/dotctrl/actions/pull.py
snakypy/dotctrl/actions/repo.py
snakypy/dotctrl/actions/restore.py
snakypy/dotctrl/actions/unlink.py
snakypy/dotctrl/config/__init__.py
snakypy/dotctrl/config/base.py
snakypy/dotctrl/config/config.py
snakypy/dotctrl/config/lang.py
snakypy/dotctrl/config/menu.py
snakypy/dotctrl/config/readme.py
snakypy/dotctrl/dotctrl.py
snakypy/dotctrl/utils/__init__.py
snakypy/dotctrl/utils/catch.py
snakypy/dotctrl/utils/checking.py
snakypy/dotctrl/utils/colors.py
snakypy/dotctrl/utils/decorators.py
snakypy/dotctrl/utils/dialog.py
snakypy/dotctrl/utils/messages.py
snakypy/dotctrl/utils/modifiers.py
snakypy/dotctrl/utils/path.py
snakypy/dotctrl/utils/process.py
dotctrl-2.0.1.dist-info/entry_points.txt
dotctrl-2.0.1.dist-info/LICENSE
dotctrl-2.0.1.dist-info/WHEEL
dotctrl-2.0.1.dist-info/METADATA
dotctrl-2.0.1.dist-info/RECORD
