Metadata-Version: 2.1
Name: dotctrl
Version: 2.0.1
Summary: Dotctrl is a package for managing your dotfiles on Linux.
Home-page: https://github.com/snakypy/dotctrl
License: MIT
Keywords: dotfiles,snakypy,dot,linux
Author: William C. Canin
Author-email: william.costa.canin@gmail.com
Requires-Python: >=3.9,<4.0
Classifier: Environment :: Console
Classifier: Intended Audience :: Developers
Classifier: License :: OSI Approved :: MIT License
Classifier: Operating System :: MacOS
Classifier: Operating System :: POSIX :: Linux
Classifier: Programming Language :: Python :: 3
Classifier: Programming Language :: Python :: 3.9
Classifier: Programming Language :: Python :: 3.10
Classifier: Programming Language :: Python :: 3.11
Classifier: Programming Language :: Python :: 3
Requires-Dist: docopt (>=0.6.2,<0.7.0)
Requires-Dist: snakypy-helpers (>=0.3.1,<0.4.0)
Requires-Dist: tomlkit (>=0.11.1,<0.12.0)
Project-URL: Bug Tracker, https://github.com/snakypy/dotctrl/issues
Project-URL: Repository, https://github.com/snakypy/dotctrl
